odoo9_addon_module_prototyper-9.0.0.1.0-py2.7-nspkg.pth
odoo_addons/module_prototyper/__openerp__.py
odoo_addons/module_prototyper/__init__.py
odoo_addons/module_prototyper/README.rst
odoo_addons/module_prototyper/security/ir.model.access.csv
odoo_addons/module_prototyper/models/module_prototyper.py
odoo_addons/module_prototyper/models/__init__.py
odoo_addons/module_prototyper/models/licenses.py
odoo_addons/module_prototyper/models/ir_model_fields.py
odoo_addons/module_prototyper/templates/8.0/__init__.py.template
odoo_addons/module_prototyper/templates/8.0/header.template
odoo_addons/module_prototyper/templates/8.0/__openerp__.py.template
odoo_addons/module_prototyper/templates/8.0/security/model_name.xml.template
odoo_addons/module_prototyper/templates/8.0/security/ir.model.access.csv.template
odoo_addons/module_prototyper/templates/8.0/models/model_name.py.template
odoo_addons/module_prototyper/templates/8.0/models/__init__.py.template
odoo_addons/module_prototyper/templates/8.0/views/model_views.xml.template
odoo_addons/module_prototyper/templates/8.0/views/model_menus.xml.template
odoo_addons/module_prototyper/templates/8.0/data/model_name.xml.template
odoo_addons/module_prototyper/templates/8.0/demo/model_name.xml.template
odoo_addons/module_prototyper/i18n/module_prototyper.pot
odoo_addons/module_prototyper/i18n/fr.po
odoo_addons/module_prototyper/wizard/module_prototyper_module_export_view.xml
odoo_addons/module_prototyper/wizard/__init__.py
odoo_addons/module_prototyper/wizard/module_prototyper_module_export.py
odoo_addons/module_prototyper/views/module_prototyper_view.xml
odoo_addons/module_prototyper/views/ir_model_fields_view.xml
odoo_addons/module_prototyper/data/README.rst
odoo_addons/module_prototyper/tests/test_prototype.py
odoo_addons/module_prototyper/tests/test_prototype_module_export.py
odoo_addons/module_prototyper/tests/__init__.py
odoo_addons/module_prototyper/static/description/icon.png
odoo9_addon_module_prototyper-9.0.0.1.0.dist-info/top_level.txt
odoo9_addon_module_prototyper-9.0.0.1.0.dist-info/WHEEL
odoo9_addon_module_prototyper-9.0.0.1.0.dist-info/RECORD
odoo9_addon_module_prototyper-9.0.0.1.0.dist-info/metadata.json
odoo9_addon_module_prototyper-9.0.0.1.0.dist-info/DESCRIPTION.rst
odoo9_addon_module_prototyper-9.0.0.1.0.dist-info/METADATA
odoo9_addon_module_prototyper-9.0.0.1.0.dist-info/namespace_packages.txt
